bundlecraft/README.md
bundlecraft/__init__.py
bundlecraft/_version.py
bundlecraft/build_all.py
bundlecraft/builder.py
bundlecraft/cli.py
bundlecraft/converter.py
bundlecraft/differ.py
bundlecraft/fetch.py
bundlecraft/verifier.py
bundlecraft/fetchers/__init__.py
bundlecraft/fetchers/api.py
bundlecraft/fetchers/azure_blob.py
bundlecraft/fetchers/gcs.py
bundlecraft/fetchers/http.py
bundlecraft/fetchers/mozilla.py
bundlecraft/fetchers/s3.py
bundlecraft/fetchers/vault.py
bundlecraft/helpers/__init__.py
bundlecraft/helpers/atomic_build.py
bundlecraft/helpers/config_schema.py
bundlecraft/helpers/convert_utils.py
bundlecraft/helpers/exit_codes.py
bundlecraft/helpers/fetch_utils.py
bundlecraft/helpers/json_output.py
bundlecraft/helpers/sbom.py
bundlecraft/helpers/signing.py
bundlecraft/helpers/template_utils.py
bundlecraft/helpers/ui.py
bundlecraft/helpers/utils.py
bundlecraft/helpers/verify_utils.py
bundlecraft-0.3.0.dist-info/METADATA
bundlecraft-0.3.0.dist-info/WHEEL
bundlecraft-0.3.0.dist-info/entry_points.txt
bundlecraft-0.3.0.dist-info/licenses/LICENSE
bundlecraft-0.3.0.dist-info/RECORD
