Metadata-Version: 2.4
Name: bundlecraft
Version: 0.3.0
Summary: Modern tool for building and managing CA trust bundles across multiple formats and environments
Project-URL: Homepage, https://github.com/bundlecraft-io/bundlecraft
Project-URL: Documentation, https://github.com/bundlecraft-io/bundlecraft#readme
Project-URL: Repository, https://github.com/bundlecraft-io/bundlecraft
Project-URL: Issues, https://github.com/bundlecraft-io/bundlecraft/issues
Project-URL: Changelog, https://github.com/bundlecraft-io/bundlecraft/releases/tag/v0.3.0
Author-email: "BundleCraft.io" <hello@bundlecraft.io>
Maintainer-email: "BundleCraft.io" <hello@bundlecraft.io>
License: MIT
License-File: LICENSE
Keywords: ca-bundle,certificates,cryptography,pki,security,trust-store
Classifier: Development Status :: 3 - Alpha
Classifier: Intended Audience :: Developers
Classifier: Intended Audience :: System Administrators
Classifier: License :: OSI Approved :: MIT License
Classifier: Operating System :: OS Independent
Classifier: Programming Language :: Python :: 3
Classifier: Programming Language :: Python :: 3.9
Classifier: Programming Language :: Python :: 3.10
Classifier: Programming Language :: Python :: 3.11
Classifier: Programming Language :: Python :: 3.12
Classifier: Topic :: Security
Classifier: Topic :: Security :: Cryptography
Classifier: Topic :: System :: Systems Administration
Requires-Python: >=3.9
Requires-Dist: azure-identity>=1.12.0
Requires-Dist: azure-storage-blob>=12.0.0
Requires-Dist: boto3>=1.26.0
Requires-Dist: click<9.0,>=8.0
Requires-Dist: cryptography<50.0,>=42.0
Requires-Dist: cyclonedx-bom<8.0,>=4.0.0
Requires-Dist: google-cloud-storage>=2.0.0
Requires-Dist: hvac>=2.0.0
Requires-Dist: pydantic<3.0,>=2.0
Requires-Dist: pyjks>=20.0.0
Requires-Dist: pyopenssl<26.0,>=23.0
Requires-Dist: python-gnupg<1.0,>=0.5.0
Requires-Dist: pyyaml<7.0,>=6.0
Provides-Extra: dev
Requires-Dist: black>=24.0.0; extra == 'dev'
Requires-Dist: build>=1.2.2; extra == 'dev'
Requires-Dist: flasgger>=0.9.7; extra == 'dev'
Requires-Dist: flask>=3.0.0; extra == 'dev'
Requires-Dist: pip-tools<8.0.0,>=7.0.0; extra == 'dev'
Requires-Dist: pip<25.0,>=21.2; extra == 'dev'
Requires-Dist: pre-commit>=3.7.0; extra == 'dev'
Requires-Dist: pytest-cov>=4.1.0; extra == 'dev'
Requires-Dist: pytest-mock>=3.11.1; extra == 'dev'
Requires-Dist: pytest>=8.0.0; extra == 'dev'
Requires-Dist: ruff>=0.14.0; extra == 'dev'
Requires-Dist: twine>=5.0.0; extra == 'dev'
Requires-Dist: yamlfix>=1.17.0; extra == 'dev'
Requires-Dist: yamllint>=1.35.0; extra == 'dev'
Provides-Extra: fetchers
Requires-Dist: google-cloud-storage>=2.0.0; extra == 'fetchers'
Requires-Dist: hvac>=2.0.0; extra == 'fetchers'
